cryptnoxpy/__init__.py
cryptnoxpy/binary_utils.py
cryptnoxpy/connection.py
cryptnoxpy/crypto_utils.py
cryptnoxpy/enums.py
cryptnoxpy/exceptions.py
cryptnoxpy/factory.py
cryptnoxpy/reader.py
cryptnoxpy/card/__init__.py
cryptnoxpy/card/authenticity.py
cryptnoxpy/card/base.py
cryptnoxpy/card/basic_g1.py
cryptnoxpy/card/custom_bits.py
cryptnoxpy/card/nft.py
cryptnoxpy/card/user_data.py
cryptnoxpy/cryptos/__init__.py
cryptnoxpy/cryptos/main.py
cryptnoxpy/cryptos/py2specials.py
cryptnoxpy/cryptos/py3specials.py
cryptnoxpy/cryptos/ripemd.py
cryptnoxpy-2.5.6.dist-info/licenses/LICENSE
cryptnoxpy-2.5.6.dist-info/METADATA
cryptnoxpy-2.5.6.dist-info/WHEEL
cryptnoxpy-2.5.6.dist-info/top_level.txt
cryptnoxpy-2.5.6.dist-info/RECORD
