Metadata-Version: 2.4
Name: cryptnoxpy
Version: 2.5.6
Home-page: https://www.cryptnox.com/
Author: Cryptnox SA
Author-email: info@cryptnox.ch
License: LGPLv3+
Project-URL: Source Code, https://github.com/Cryptnox-Software/cryptnoxpy
Keywords: python,cryptography
Platform: any
Classifier: Development Status :: 4 - Beta
Classifier: Intended Audience :: Developers
Classifier: License :: OSI Approved :: GNU Lesser General Public License v3 (LGPLv3)
Classifier: License :: Other/Proprietary License
Classifier: Operating System :: OS Independent
Classifier: Programming Language :: Python :: 3.11
Classifier: Programming Language :: Python :: 3.12
Classifier: Topic :: Security :: Cryptography
Classifier: Topic :: Software Development :: Libraries :: Python Modules
Requires-Python: <=3.13.7,>=3.11
License-File: LICENSE
Requires-Dist: aiohttp
Requires-Dist: cryptography
Requires-Dist: pyscard
Dynamic: description
Dynamic: description-content-type
Dynamic: license-file
Dynamic: requires-dist
